{
  "contest": {
    "id": 173,
    "name": "Croc Champ 2012 - Round 1",
    "type": "CF",
    "phase": "FINISHED",
    "frozen": false,
    "durationSeconds": 7200,
    "startTimeSeconds": 1333724400,
    "relativeTimeSeconds": 434630233
  },
  "problems": [
    {
      "contestId": 173,
      "index": "E",
      "name": "Camping Groups",
      "type": "PROGRAMMING",
      "points": 2500.0,
      "rating": 2600,
      "tags": [
        "data structures",
        "sortings"
      ]
    },
    {
      "contestId": 173,
      "index": "D",
      "name": "Deputies",
      "type": "PROGRAMMING",
      "points": 2000.0,
      "rating": 2500,
      "tags": [
        "constructive algorithms",
        "graphs",
        "greedy",
        "implementation"
      ]
    },
    {
      "contestId": 173,
      "index": "C",
      "name": "Spiral Maximum",
      "type": "PROGRAMMING",
      "points": 1500.0,
      "rating": 1900,
      "tags": [
        "brute force",
        "dp"
      ]
    },
    {
      "contestId": 173,
      "index": "B",
      "name": "Chamber of Secrets",
      "type": "PROGRAMMING",
      "points": 1000.0,
      "rating": 1800,
      "tags": [
        "dfs and similar",
        "shortest paths"
      ]
    },
    {
      "contestId": 173,
      "index": "A",
      "name": "Rock-Paper-Scissors",
      "type": "PROGRAMMING",
      "points": 500.0,
      "rating": 1300,
      "tags": [
        "implementation",
        "math"
      ]
    }
  ]
}