{
  "contest": {
    "id": 203,
    "name": "Codeforces Round 128 (Div. 2)",
    "type": "CF",
    "phase": "FINISHED",
    "frozen": false,
    "durationSeconds": 7200,
    "startTimeSeconds": 1341329400,
    "relativeTimeSeconds": 427025233
  },
  "problems": [
    {
      "contestId": 203,
      "index": "E",
      "name": "Transportation",
      "type": "PROGRAMMING",
      "points": 2500.0,
      "rating": 2300,
      "tags": [
        "greedy",
        "sortings",
        "two pointers"
      ]
    },
    {
      "contestId": 203,
      "index": "D",
      "name": "Hit Ball",
      "type": "PROGRAMMING",
      "points": 2000.0,
      "rating": 1700,
      "tags": [
        "geometry",
        "implementation",
        "math"
      ]
    },
    {
      "contestId": 203,
      "index": "C",
      "name": "Photographer",
      "type": "PROGRAMMING",
      "points": 1500.0,
      "rating": 1400,
      "tags": [
        "greedy",
        "sortings"
      ]
    },
    {
      "contestId": 203,
      "index": "B",
      "name": "Game on Paper",
      "type": "PROGRAMMING",
      "points": 1000.0,
      "rating": 1300,
      "tags": [
        "brute force",
        "implementation"
      ]
    },
    {
      "contestId": 203,
      "index": "A",
      "name": "Two Problems",
      "type": "PROGRAMMING",
      "points": 500.0,
      "rating": 1200,
      "tags": [
        "brute force",
        "implementation"
      ]
    }
  ]
}