{
  "contest": {
    "id": 205,
    "name": "Codeforces Round 129 (Div. 2)",
    "type": "CF",
    "phase": "FINISHED",
    "frozen": false,
    "durationSeconds": 7200,
    "startTimeSeconds": 1342020600,
    "relativeTimeSeconds": 426334033
  },
  "problems": [
    {
      "contestId": 205,
      "index": "B",
      "name": "Little Elephant and Sorting",
      "type": "PROGRAMMING",
      "points": 1000.0,
      "rating": 1400,
      "tags": [
        "brute force",
        "greedy"
      ]
    },
    {
      "contestId": 205,
      "index": "A",
      "name": "Little Elephant and Rozdil",
      "type": "PROGRAMMING",
      "points": 500.0,
      "rating": 900,
      "tags": [
        "brute force",
        "implementation"
      ]
    }
  ]
}