{
  "contest": {
    "id": 626,
    "name": "8VC Venture Cup 2016 - Elimination Round",
    "type": "CF",
    "phase": "FINISHED",
    "frozen": false,
    "durationSeconds": 9000,
    "startTimeSeconds": 1455384900,
    "relativeTimeSeconds": 312969732
  },
  "problems": [
    {
      "contestId": 626,
      "index": "G",
      "name": "Raffles",
      "type": "PROGRAMMING",
      "points": 3000.0,
      "rating": 3100,
      "tags": [
        "data structures",
        "dp",
        "greedy",
        "math"
      ]
    },
    {
      "contestId": 626,
      "index": "F",
      "name": "Group Projects",
      "type": "PROGRAMMING",
      "points": 2500.0,
      "rating": 2400,
      "tags": [
        "dp"
      ]
    },
    {
      "contestId": 626,
      "index": "E",
      "name": "Simple Skewness",
      "type": "PROGRAMMING",
      "points": 2000.0,
      "rating": 2400,
      "tags": [
        "binary search",
        "math",
        "ternary search"
      ]
    },
    {
      "contestId": 626,
      "index": "D",
      "name": "Jerry's Protest",
      "type": "PROGRAMMING",
      "points": 1500.0,
      "rating": 1800,
      "tags": [
        "brute force",
        "combinatorics",
        "dp",
        "probabilities"
      ]
    },
    {
      "contestId": 626,
      "index": "C",
      "name": "Block Towers",
      "type": "PROGRAMMING",
      "points": 1000.0,
      "rating": 1600,
      "tags": [
        "brute force",
        "greedy",
        "math",
        "number theory"
      ]
    },
    {
      "contestId": 626,
      "index": "B",
      "name": "Cards",
      "type": "PROGRAMMING",
      "points": 750.0,
      "rating": 1300,
      "tags": [
        "constructive algorithms",
        "dp",
        "math"
      ]
    },
    {
      "contestId": 626,
      "index": "A",
      "name": "Robot Sequence",
      "type": "PROGRAMMING",
      "points": 500.0,
      "rating": 1000,
      "tags": [
        "brute force",
        "implementation"
      ]
    }
  ]
}